etools_validator/__init__.py
etools_validator/decorators.py
etools_validator/exceptions.py
etools_validator/mixins.py
etools_validator/parsers.py
etools_validator/utils.py
etools_validator/validation.py
etools_validator-0.5.dist-info/LICENSE
etools_validator-0.5.dist-info/METADATA
etools_validator-0.5.dist-info/WHEEL
etools_validator-0.5.dist-info/top_level.txt
etools_validator-0.5.dist-info/RECORD
